valvepcf/__init__.py
valvepcf/classes.py
valvepcf/constants.py
valvepcf/loader.py
valvepcf/pcf.py
valvepcf/structs.py
valvepcf/unloader.py
valvepcf-1.1.2.dist-info/LICENSE
valvepcf-1.1.2.dist-info/METADATA
valvepcf-1.1.2.dist-info/WHEEL
valvepcf-1.1.2.dist-info/top_level.txt
valvepcf-1.1.2.dist-info/RECORD
